{
  "v": 1,
  "name": "campfire",
  "folders": [],
  "requests": [
    {
      "v": "1",
      "name": "01 Health",
      "method": "GET",
      "endpoint": "<<baseUrl>>/api/v1/health",
      "params": [],
      "headers": [],
      "preRequestScript": "",
      "testScript": "",
      "auth": { "authType": "none", "authActive": true },
      "body": { "contentType": null, "body": null }
    },
    {
      "v": "1",
      "name": "02 List users",
      "method": "GET",
      "endpoint": "<<baseUrl>>/api/v1/users",
      "params": [],
      "headers": [
        { "key": "X-User-Id", "value": "<<userId>>", "active": true }
      ],
      "preRequestScript": "",
      "testScript": "",
      "auth": { "authType": "none", "authActive": true },
      "body": { "contentType": null, "body": null }
    },
    {
      "v": "1",
      "name": "03 Me",
      "method": "GET",
      "endpoint": "<<baseUrl>>/api/v1/users/me",
      "params": [],
      "headers": [
        { "key": "X-User-Id", "value": "<<userId>>", "active": true }
      ],
      "preRequestScript": "",
      "testScript": "",
      "auth": { "authType": "none", "authActive": true },
      "body": { "contentType": null, "body": null }
    },
    {
      "v": "1",
      "name": "04 Search songs",
      "method": "GET",
      "endpoint": "<<baseUrl>>/api/v1/songs/search",
      "params": [
        { "key": "q", "value": "beatles", "active": true },
        { "key": "limit", "value": "20", "active": true }
      ],
      "headers": [
        { "key": "X-User-Id", "value": "<<userId>>", "active": true }
      ],
      "preRequestScript": "",
      "testScript": "",
      "auth": { "authType": "none", "authActive": true },
      "body": { "contentType": null, "body": null }
    },
    {
      "v": "1",
      "name": "05 List instruments",
      "method": "GET",
      "endpoint": "<<baseUrl>>/api/v1/instruments",
      "params": [
        { "key": "query", "value": "guitar", "active": true },
        { "key": "limit", "value": "50", "active": true }
      ],
      "headers": [
        { "key": "X-User-Id", "value": "<<userId>>", "active": true }
      ],
      "preRequestScript": "",
      "testScript": "",
      "auth": { "authType": "none", "authActive": true },
      "body": { "contentType": null, "body": null }
    },
    {
      "v": "1",
      "name": "06 Register repertoire",
      "method": "POST",
      "endpoint": "<<baseUrl>>/api/v1/repertoire",
      "params": [],
      "headers": [
        { "key": "X-User-Id", "value": "<<userId>>", "active": true },
        { "key": "Content-Type", "value": "application/json", "active": true }
      ],
      "preRequestScript": "",
      "testScript": "",
      "auth": { "authType": "none", "authActive": true },
      "body": {
        "contentType": "application/json",
        "body": "{\n  \"song_title\": \"Black\",\n  \"song_artist\": \"Pearl Jam\",\n  \"instrument\": \"guitar\",\n  \"proficiency\": 8\n}"
      }
    },
    {
      "v": "1",
      "name": "07 My repertoire",
      "method": "GET",
      "endpoint": "<<baseUrl>>/api/v1/repertoire/me",
      "params": [],
      "headers": [
        { "key": "X-User-Id", "value": "<<userId>>", "active": true }
      ],
      "preRequestScript": "",
      "testScript": "",
      "auth": { "authType": "none", "authActive": true },
      "body": { "contentType": null, "body": null }
    }
  ]
}
